Metadata-Version: 2.1
Name: python-byterestclient-hypernode
Version: 20211130.1427
Summary: A generic REST client
Home-page: https://github.com/ByteInternet/python-byterestclient
Author: Byte B.V.
Author-email: tech@byte.nl
License: UNKNOWN
Keywords: REST client requests json API
Platform: UNKNOWN
Classifier: Development Status :: 5 - Production/Stable
Classifier: License :: OSI Approved :: MIT License
Classifier: Intended Audience :: Developers
Classifier: Topic :: Utilities
Classifier: Topic :: Communications
Classifier: Topic :: Internet
Classifier: Programming Language :: Python :: 2
Classifier: Programming Language :: Python :: 2.6
Classifier: Programming Language :: Python :: 2.7
Requires-Dist: requests
